swarms_cloud/__init__.py
swarms_cloud/main.py
swarms_cloud-0.4.5.dist-info/LICENSE
swarms_cloud-0.4.5.dist-info/METADATA
swarms_cloud-0.4.5.dist-info/WHEEL
swarms_cloud-0.4.5.dist-info/RECORD
